pysfn/__init__.py
pysfn/condition.py
pysfn/function.py
pysfn/lmbda.py
pysfn/service_operations.py
pysfn/steps.py
pysfn-0.1.13.dist-info/METADATA
pysfn-0.1.13.dist-info/WHEEL
pysfn-0.1.13.dist-info/RECORD
