Metadata-Version: 2.1
Name: pysfn
Version: 0.1.13
Summary: Transpiler for AWS Step Functions
License: MIT
Author: Dave Schultz
Author-email: dave@daveschultzconsulting.com
Requires-Python: >=3.9,<4.0
Classifier: License :: OSI Approved :: MIT License
Classifier: Programming Language :: Python :: 3
Classifier: Programming Language :: Python :: 3.9
Classifier: Programming Language :: Python :: 3.10
Classifier: Programming Language :: Python :: 3.11
Requires-Dist: aws-cdk-lib (>=2.55.1,<3.0.0)
Requires-Dist: constructs (>=10.1.194,<11.0.0)
Requires-Dist: shortuuid (>=1.0.11,<2.0.0)
